ctrtools/__init__.py
ctrtools/ctricon.py
ctrtools-0.1.0.dist-info/METADATA
ctrtools-0.1.0.dist-info/WHEEL
ctrtools-0.1.0.dist-info/entry_points.txt
ctrtools-0.1.0.dist-info/top_level.txt
ctrtools-0.1.0.dist-info/RECORD
